hyperpod_pytorch_job_template/__init__.py
hyperpod_pytorch_job_template/registry.py
hyperpod_pytorch_job_template/v1_0/__init__.py
hyperpod_pytorch_job_template/v1_0/model.py
hyperpod_pytorch_job_template/v1_0/schema.json
hyperpod_pytorch_job_template/v1_0/template.py
hyperpod_pytorch_job_template/v1_1/__init__.py
hyperpod_pytorch_job_template/v1_1/model.py
hyperpod_pytorch_job_template/v1_1/schema.json
hyperpod_pytorch_job_template/v1_1/template.py
hyperpod_pytorch_job_template-1.3.0.dist-info/licenses/LICENSE
hyperpod_pytorch_job_template-1.3.0.dist-info/METADATA
hyperpod_pytorch_job_template-1.3.0.dist-info/WHEEL
hyperpod_pytorch_job_template-1.3.0.dist-info/top_level.txt
hyperpod_pytorch_job_template-1.3.0.dist-info/RECORD
