Metadata-Version: 2.4
Name: hyperpod-pytorch-job-template
Version: 1.3.0
Summary: Versioned JSON-schema + Pydantic models for HyperpodPytorchJobOperator
Author: Amazon Web Services
License: Apache-2.0
Requires-Python: >=3.8
License-File: LICENSE
Requires-Dist: pydantic
Dynamic: license-file
